ferramentas_basicas_pln/__init__.py
ferramentas_basicas_pln/main.py
ferramentas_basicas_pln-0.9.9.8.dist-info/METADATA
ferramentas_basicas_pln-0.9.9.8.dist-info/WHEEL
ferramentas_basicas_pln-0.9.9.8.dist-info/top_level.txt
ferramentas_basicas_pln-0.9.9.8.dist-info/RECORD
