Metadata-Version: 2.1
Name: ferramentas-basicas-pln
Version: 0.9.9.8
Summary: Kit de ferramentas para processos básicos de Processamento de Linguagem Natural.
Author: Igor Caetano de Souza
Project-URL: GitHub Repository, https://github.com/IgorCaetano/ferramentas_basicas_pln
Requires-Dist: regex
